odoo/addons/partner_pricelist_search/README.rst
odoo/addons/partner_pricelist_search/__init__.py
odoo/addons/partner_pricelist_search/__manifest__.py
odoo/addons/partner_pricelist_search/i18n/es.po
odoo/addons/partner_pricelist_search/i18n/hr.po
odoo/addons/partner_pricelist_search/i18n/it.po
odoo/addons/partner_pricelist_search/i18n/partner_pricelist_search.pot
odoo/addons/partner_pricelist_search/models/__init__.py
odoo/addons/partner_pricelist_search/models/product_pricelist.py
odoo/addons/partner_pricelist_search/models/res_partner.py
odoo/addons/partner_pricelist_search/readme/CONTRIBUTORS.md
odoo/addons/partner_pricelist_search/readme/CREDITS.md
odoo/addons/partner_pricelist_search/readme/DESCRIPTION.md
odoo/addons/partner_pricelist_search/readme/ROADMAP.md
odoo/addons/partner_pricelist_search/static/description/icon.png
odoo/addons/partner_pricelist_search/static/description/index.html
odoo/addons/partner_pricelist_search/tests/__init__.py
odoo/addons/partner_pricelist_search/tests/test_partner_pricelist_search.py
odoo/addons/partner_pricelist_search/views/product_pricelist_views.xml
odoo_addon_partner_pricelist_search-18.0.1.0.0.3.dist-info/METADATA
odoo_addon_partner_pricelist_search-18.0.1.0.0.3.dist-info/WHEEL
odoo_addon_partner_pricelist_search-18.0.1.0.0.3.dist-info/top_level.txt
odoo_addon_partner_pricelist_search-18.0.1.0.0.3.dist-info/RECORD
